test_poetry/__init__.py
hm_test_poetry-0.1.0.dist-info/METADATA
hm_test_poetry-0.1.0.dist-info/WHEEL
hm_test_poetry-0.1.0.dist-info/RECORD
