Metadata-Version: 2.4
Name: hm-test-poetry
Version: 0.1.0
Summary: 
Author: Hank Murdock
Author-email: hankmurdock@gmail.com
Requires-Python: >=3.12
Classifier: Programming Language :: Python :: 3
Classifier: Programming Language :: Python :: 3.12
Classifier: Programming Language :: Python :: 3.13
Classifier: Programming Language :: Python :: 3.14
Requires-Dist: numpy (>=2.4.1,<3.0.0)
Requires-Dist: pandas (>=3.0.0,<4.0.0)
